jinja2_fragments/__init__.py
jinja2_fragments/fastapi.py
jinja2_fragments/flask.py
jinja2_fragments/litestar.py
jinja2_fragments/py.typed
jinja2_fragments/quart.py
jinja2_fragments/sanic.py
jinja2_fragments-1.10.0.dist-info/licenses/LICENSE
jinja2_fragments-1.10.0.dist-info/METADATA
jinja2_fragments-1.10.0.dist-info/WHEEL
jinja2_fragments-1.10.0.dist-info/top_level.txt
jinja2_fragments-1.10.0.dist-info/RECORD
