Metadata-Version: 2.4
Name: jinja2_fragments
Version: 1.10.0
Summary: Render Jinja2 template block as HTML page fragments on Python web frameworks.
Author-email: Sergi Pons Freixes <sergi@cub3.net>
License-Expression: MIT
Project-URL: Homepage, https://jinja2-fragments.readthedocs.io/
Project-URL: Source Code, https://github.com/sponsfreixes/jinja2-fragments
Project-URL: Issue Tracker, https://github.com/sponsfreixes/jinja2-fragments/issues
Project-URL: Changes, https://github.com/sponsfreixes/jinja2-fragments/blob/main/CHANGELOG.md
Classifier: Development Status :: 5 - Production/Stable
Classifier: Environment :: Web Environment
Classifier: Framework :: Flask
Classifier: Framework :: FastAPI
Classifier: Intended Audience :: Developers
Classifier: Operating System :: OS Independent
Classifier: Programming Language :: Python
Classifier: Programming Language :: Python :: 3
Classifier: Topic :: Internet :: WWW/HTTP :: Dynamic Content
Classifier: Topic :: Text Processing :: Markup :: HTML
Requires-Python: >=3.9
License-File: LICENSE
Requires-Dist: jinja2<4.0.0,>=3.1.0
Dynamic: license-file
